[
    {
        "key": "dbln",
        "value": "%7B%22100070829062788%22%3A%22a0BwqQHY%22%7D",
        "domain": "facebook.com",
        "path": "/login/device-based/",
        "hostOnly": false,
        "creation": "2025-10-08T18:10:19.142Z",
        "lastAccessed": "2025-10-08T18:10:19.143Z"
    },
    {
        "key": "sb",
        "value": "qovuZ-BRmRApg7HqOIwsz3bH",
        "domain": "facebook.com",
        "path": "/",
        "hostOnly": false,
        "creation": "2025-10-08T18:10:19.143Z",
        "lastAccessed": "2025-10-08T18:10:19.143Z"
    },
    {
        "key": "datr",
        "value": "20DZaGKKPAke3gz3tRvPNdT_",
        "domain": "facebook.com",
        "path": "/",
        "hostOnly": false,
        "creation": "2025-10-08T18:10:19.143Z",
        "lastAccessed": "2025-10-08T18:10:19.143Z"
    },
    {
        "key": "ps_l",
        "value": "1",
        "domain": "facebook.com",
        "path": "/",
        "hostOnly": false,
        "creation": "2025-10-08T18:10:19.143Z",
        "lastAccessed": "2025-10-08T18:10:19.143Z"
    },
    {
        "key": "ps_n",
        "value": "1",
        "domain": "facebook.com",
        "path": "/",
        "hostOnly": false,
        "creation": "2025-10-08T18:10:19.143Z",
        "lastAccessed": "2025-10-08T18:10:19.143Z"
    },
    {
        "key": "dpr",
        "value": "3.69307279586792",
        "domain": "facebook.com",
        "path": "/",
        "hostOnly": false,
        "creation": "2025-10-08T18:10:19.143Z",
        "lastAccessed": "2025-10-08T18:10:19.143Z"
    },
    {
        "key": "c_user",
        "value": "100064642667725",
        "domain": "facebook.com",
        "path": "/",
        "hostOnly": false,
        "creation": "2025-10-08T18:10:19.143Z",
        "lastAccessed": "2025-10-08T18:10:19.143Z"
    },
    {
        "key": "xs",
        "value": "5%3APCGjg9GcPYx8Cg%3A2%3A1759946227%3A-1%3A-1",
        "domain": "facebook.com",
        "path": "/",
        "hostOnly": false,
        "creation": "2025-10-08T18:10:19.143Z",
        "lastAccessed": "2025-10-08T18:10:19.143Z"
    },
    {
        "key": "fr",
        "value": "0WZIeyA67oSvMPfDw.AWdAch3shFlKI3F-H3WxwlxTrqu01TK0AF_JwV5OC55t1V70eyQ.Bo2UDb..AAA.0.0.Bo5qfS.AWcGrm10NK3ySSZNQLvtiDeCkZA",
        "domain": "facebook.com",
        "path": "/",
        "hostOnly": false,
        "creation": "2025-10-08T18:10:19.143Z",
        "lastAccessed": "2025-10-08T18:10:19.143Z"
    },
    {
        "key": "presence",
        "value": "C%7B%22t3%22%3A%5B%5D%2C%22utc3%22%3A1759946718434%2C%22v%22%3A1%7D",
        "domain": "facebook.com",
        "path": "/",
        "hostOnly": false,
        "creation": "2025-10-08T18:10:19.143Z",
        "lastAccessed": "2025-10-08T18:10:19.143Z"
    },
    {
        "key": "wd",
        "value": "796x1446",
        "domain": "facebook.com",
        "path": "/",
        "hostOnly": false,
        "creation": "2025-10-08T18:10:19.143Z",
        "lastAccessed": "2025-10-08T18:10:19.143Z"
    }
]
